example/make_toy_data.py
mitoomics_gpu/__init__.py
mitoomics_gpu/__main__.py
mitoomics_gpu/cli.py
mitoomics_gpu/config.py
mitoomics_gpu/dashboard.py
mitoomics_gpu/ev_integration.py
mitoomics_gpu/gene_sets.py
mitoomics_gpu/gpu_accel.py
mitoomics_gpu/gpu_backend.py
mitoomics_gpu/gpu_cli.py
mitoomics_gpu/io.py
mitoomics_gpu/mhi.py
mitoomics_gpu/rapids_program_score.py
mitoomics_gpu/report.py
mitoomics_gpu/scoring.py
mitoomics_gpu/scverse_api.py
mitoomics_gpu/bench/benchmark_mhi.py
mitoomics_gpu/tools/add_fusion_fission_columns.py
mitoomics_gpu/tools/autostandardize_proteomics.py
mitoomics_gpu/tools/build_gene_assets.py
mitoomics_gpu/tools/build_gene_assets_from_xls_fixed.py
mitoomics_gpu/tools/build_gene_assets_from_xls_fixed.py.py
mitoomics_gpu/tools/convert_human512reports_xlsx.py
mitoomics_gpu/tools/grab_scrna_census.py
mitoomics_gpu/tools/grab_scrna_census_mito.py
mitoomics_gpu/tools/pretty_plots.py
mitoomics_gpu-0.1.2.dist-info/METADATA
mitoomics_gpu-0.1.2.dist-info/WHEEL
mitoomics_gpu-0.1.2.dist-info/top_level.txt
mitoomics_gpu-0.1.2.dist-info/RECORD
