Metadata-Version: 2.4
Name: mitoomics-gpu
Version: 0.1.2
Summary: GPU-accelerated pipeline to compute a Mitochondrial Health Index (MHI)
Classifier: Programming Language :: Python :: 3
Classifier: Programming Language :: Python :: 3 :: Only
Classifier: Programming Language :: Python :: 3.9
Classifier: Programming Language :: Python :: 3.10
Classifier: Programming Language :: Python :: 3.11
Classifier: Programming Language :: Python :: 3.12
Classifier: Programming Language :: Python :: 3.13
Requires-Python: >=3.9
Requires-Dist: numpy
Requires-Dist: pandas
Requires-Dist: anndata>=0.10
Requires-Dist: scanpy>=1.9
